cli/__init__.py
cli/cli.py
cli/info.py
cli/validator.py
cli/version.py
cli/picture/__init__.py
cli/picture/main.py
cli/review/__init__.py
cli/review/main.py
cli/service/__init__.py
cli/service/search.py
cli/service/tm.py
cli/service/wiki.py
daami_cli-0.0.20.dist-info/METADATA
daami_cli-0.0.20.dist-info/WHEEL
daami_cli-0.0.20.dist-info/entry_points.txt
daami_cli-0.0.20.dist-info/top_level.txt
daami_cli-0.0.20.dist-info/RECORD
