Metadata-Version: 2.1
Name: daami-cli
Version: 0.0.20
Summary: cli to create additional things for daamireview
Home-page: https://github.com/jungeebah/daami-cli.git
Author: DaamiReview
Author-email: daamireview@gmail.com
License: UNKNOWN
Platform: UNKNOWN
Classifier: Programming Language :: Python :: 3
Classifier: License :: OSI Approved :: MIT License
Classifier: Operating System :: OS Independent
Requires-Python: >=3.6
Requires-Dist: Click
Requires-Dist: pyaml
Requires-Dist: google-api-python-client
Requires-Dist: wikipedia
Requires-Dist: configparser
Requires-Dist: python-frontmatter
Requires-Dist: PyInquirer
Requires-Dist: IMDbPY
Requires-Dist: tmdbsimple
Requires-Dist: Pillow
